darelabdb/__init__.py
darelabdb/configurator/__init__.py
darelabdb/databases/__init__.py
darelabdb/databases/mongo/__init__.py
darelabdb/databases/postgres/__init__.py
darelabdb/engine/__init__.py
darelabdb/generative/__init__.py
darelabdb/generative/nl_search/__init__.py
darelabdb/main.py
darelabdb/optimizers/__init__.py
darelabdb/optimizers/qpseeker/__init__.py
darelabdb/recommenders/__init__.py
darelabdb/recommenders/collaborative_filtering/__init__.py
darelabdb/recommenders/query_builder/__init__.py
darelabdb/recommenders/similarity_based_rs/__init__.py
darelabdb/schemas/__init__.py
darelabdb-0.1.0.dist-info/LICENSE
darelabdb-0.1.0.dist-info/METADATA
darelabdb-0.1.0.dist-info/WHEEL
darelabdb-0.1.0.dist-info/RECORD
