Metadata-Version: 2.1
Name: darelabdb
Version: 0.1.0
Summary: 
Requires-Python: >=3.9,<4.0
Classifier: Programming Language :: Python :: 3
Classifier: Programming Language :: Python :: 3.9
Classifier: Programming Language :: Python :: 3.10
Classifier: Programming Language :: Python :: 3.11
Requires-Dist: loguru (>=0.7.2,<0.8.0)
Requires-Dist: torch (>=2.0.0,!=2.0.1,!=2.1.0)
